persistent_settings/__init__.py
persistent_settings/admin.py
persistent_settings/apps.py
persistent_settings/middlewares.py
persistent_settings/models.py
persistent_settings/management/__init__.py
persistent_settings/management/commands/__init__.py
persistent_settings/management/commands/delvar.py
persistent_settings/management/commands/getvar.py
persistent_settings/management/commands/setvar.py
persistent_settings/migrations/0001_initial.py
persistent_settings/migrations/0002_auto_20191214_2205.py
persistent_settings/migrations/0003_variable_user.py
persistent_settings/migrations/0004_auto_20191226_2223.py
persistent_settings/migrations/0005_auto_20191227_1602.py
persistent_settings/migrations/__init__.py
persistent_settings/templatetags/__init__.py
persistent_settings/templatetags/persistent_settings.py
django_persistent_settings-0.2.1.dist-info/LICENSE.txt
django_persistent_settings-0.2.1.dist-info/METADATA
django_persistent_settings-0.2.1.dist-info/WHEEL
django_persistent_settings-0.2.1.dist-info/top_level.txt
django_persistent_settings-0.2.1.dist-info/RECORD
