Metadata-Version: 2.1
Name: django-persistent-settings
Version: 0.2.1
Summary: django-persistent-settings is a library to store platform-specific settings in database.
Home-page: https://github.com/erayerdin/django-persistent-settings
Author: Eray Erdin <eraygezer.94@gmail.com>
Author-email: eraygezer.94@gmail.com
License: Apache License 2.0
Download-URL: https://github.com/erayerdin/django-persistent-settings/archive/v0.2.1.tar.gz
Keywords: django persistent stored settings
Platform: UNKNOWN
Classifier: Development Status :: 5 - Production/Stable
Classifier: Intended Audience :: Developers
Classifier: License :: OSI Approved :: Apache Software License
Classifier: Programming Language :: Python :: 3 :: Only
Classifier: Programming Language :: Python :: 3.5
Classifier: Programming Language :: Python :: 3.6
Classifier: Programming Language :: Python :: 3.7
Classifier: Programming Language :: Python :: 3.8
Classifier: Framework :: Django :: 1.11
Classifier: Framework :: Django :: 2.0
Classifier: Framework :: Django :: 2.1
Classifier: Framework :: Django :: 2.2
Classifier: Topic :: Database
Requires-Dist: django (<3,>=1.11)
